{
    "clientName": "Thunder Client",
    "collectionName": "Proyecto Final BackEnd",
    "collectionId": "acd7cf24-efe8-4c6b-887b-795995e3373b",
    "dateExported": "2024-06-28T00:57:40.140Z",
    "version": "1.2",
    "folders": [
        {
            "_id": "ca8ee083-0c7a-42e5-b127-f479196f1407",
            "name": "Alumno",
            "containerId": "",
            "created": "2024-05-05T18:12:35.219Z",
            "sortNum": 10000
        },
        {
            "_id": "d6da219b-947c-4ff8-9cad-4241c077db91",
            "name": "CREATE",
            "containerId": "ca8ee083-0c7a-42e5-b127-f479196f1407",
            "created": "2024-05-05T23:43:46.613Z",
            "sortNum": 20000
        },
        {
            "_id": "c5c675f9-2af0-4dc4-a374-3bb4702cdc6f",
            "name": "READ",
            "containerId": "ca8ee083-0c7a-42e5-b127-f479196f1407",
            "created": "2024-05-05T23:43:59.660Z",
            "sortNum": 30000
        },
        {
            "_id": "b0b7201e-c5c9-4a14-909b-6bb1285674b2",
            "name": "UPDATE",
            "containerId": "ca8ee083-0c7a-42e5-b127-f479196f1407",
            "created": "2024-05-05T23:44:11.573Z",
            "sortNum": 40000
        },
        {
            "_id": "005ff324-7ba4-421d-91b8-90121202e59f",
            "name": "DELETE",
            "containerId": "ca8ee083-0c7a-42e5-b127-f479196f1407",
            "created": "2024-05-05T23:44:19.826Z",
            "sortNum": 50000
        },
        {
            "_id": "e473ab64-6018-4927-816f-05599676b3bf",
            "name": "Docente",
            "containerId": "",
            "created": "2024-06-11T00:22:02.176Z",
            "sortNum": 60000
        },
        {
            "_id": "40dd61a0-d1f9-45ff-bd7a-9146dd3c52c8",
            "name": "CREATE",
            "containerId": "e473ab64-6018-4927-816f-05599676b3bf",
            "created": "2024-06-11T00:22:09.827Z",
            "sortNum": 70000
        },
        {
            "_id": "55ce1020-3aae-43ed-9457-7f71f44ada81",
            "name": "No Docente",
            "containerId": "",
            "created": "2024-06-19T00:07:29.903Z",
            "sortNum": 70000
        },
        {
            "_id": "8d1a19db-8fe5-4741-a48f-95730d640308",
            "name": "CREATE",
            "containerId": "55ce1020-3aae-43ed-9457-7f71f44ada81",
            "created": "2024-06-19T00:07:29.904Z",
            "sortNum": 70000
        },
        {
            "_id": "0cdee016-4572-4e9e-8a24-ace4fd3f6256",
            "name": "READ",
            "containerId": "e473ab64-6018-4927-816f-05599676b3bf",
            "created": "2024-06-11T00:22:15.949Z",
            "sortNum": 80000
        },
        {
            "_id": "0e1e6492-9623-4a2b-9873-1c4f05bd5d60",
            "name": "READ",
            "containerId": "55ce1020-3aae-43ed-9457-7f71f44ada81",
            "created": "2024-06-19T00:07:29.905Z",
            "sortNum": 80000
        },
        {
            "_id": "b6256980-540b-4557-84a7-a2323ab6a60f",
            "name": "UPDATE",
            "containerId": "e473ab64-6018-4927-816f-05599676b3bf",
            "created": "2024-06-11T00:22:22.207Z",
            "sortNum": 90000
        },
        {
            "_id": "beeec0b9-c389-4e5d-891d-29b3afd81c2a",
            "name": "UPDATE",
            "containerId": "55ce1020-3aae-43ed-9457-7f71f44ada81",
            "created": "2024-06-19T00:07:29.906Z",
            "sortNum": 90000
        },
        {
            "_id": "8237cd96-29ba-4126-be73-e3774cf164c2",
            "name": "DELETE",
            "containerId": "e473ab64-6018-4927-816f-05599676b3bf",
            "created": "2024-06-11T00:22:27.836Z",
            "sortNum": 100000
        },
        {
            "_id": "38030b89-2218-4627-840c-32124c7d5292",
            "name": "DELETE",
            "containerId": "55ce1020-3aae-43ed-9457-7f71f44ada81",
            "created": "2024-06-19T00:07:29.907Z",
            "sortNum": 100000
        },
        {
            "_id": "96019cad-eb15-4414-a8e1-c5636a8325c7",
            "name": "Art Api",
            "containerId": "",
            "created": "2024-06-19T01:15:47.498Z",
            "sortNum": 110000
        },
        {
            "_id": "403a51f5-3e12-40af-944b-e7a1a8bb324f",
            "name": "Obras de arte",
            "containerId": "96019cad-eb15-4414-a8e1-c5636a8325c7",
            "created": "2024-06-19T01:33:30.988Z",
            "sortNum": 120000
        },
        {
            "_id": "ac8e27a3-3a81-4e0a-a3a8-0864646e97c3",
            "name": "Artistas",
            "containerId": "96019cad-eb15-4414-a8e1-c5636a8325c7",
            "created": "2024-06-19T01:33:43.198Z",
            "sortNum": 130000
        },
        {
            "_id": "d608f91a-2d32-482a-a07e-d829c7530543",
            "name": "Countries Api",
            "containerId": "",
            "created": "2024-06-19T01:55:22.864Z",
            "sortNum": 130000
        },
        {
            "_id": "46483a8d-9564-4ce1-ba2e-005391676123",
            "name": "Login/Register",
            "containerId": "",
            "created": "2024-06-20T17:14:51.160Z",
            "sortNum": 140000
        }
    ],
    "requests": [
        {
            "_id": "63525546-d3d4-4b13-af15-151aad86c237",
            "colId": "acd7cf24-efe8-4c6b-887b-795995e3373b",
            "containerId": "c5c675f9-2af0-4dc4-a374-3bb4702cdc6f",
            "name": "lista de alumnos",
            "url": "http://localhost:8080/alumnos",
            "method": "GET",
            "sortNum": 10000,
            "created": "2024-05-05T18:12:56.740Z",
            "modified": "2024-06-28T00:50:26.643Z",
            "headers": [
                {
                    "name": "Authorization",
                    "value": "eyJhbGciOiJIUzI1NiIsInR5cCI6IkpXVCJ9.eyJ1c2VySWQiOiI2Njc5ZDAyOTkzYmNjMjBiNzkzYTM3YzYiLCJyb2xlIjoiYWRtaW4iLCJpYXQiOjE3MTk1MzU3NzcsImV4cCI6MTcxOTUzOTM3N30.q2lfxfRNpAX-r3ErqC04737Fn5AkP0-xqJTAolhnJ9w"
                }
            ]
        },
        {
            "_id": "40530e46-42bf-4c15-8c20-daa27dcb8b4d",
            "colId": "acd7cf24-efe8-4c6b-887b-795995e3373b",
            "containerId": "d6da219b-947c-4ff8-9cad-4241c077db91",
            "name": "crear alumno",
            "url": "http://localhost:8080/alumnos/new-alumno",
            "method": "POST",
            "sortNum": 10000,
            "created": "2024-05-05T23:33:53.991Z",
            "modified": "2024-06-28T00:49:59.050Z",
            "headers": [
                {
                    "name": "Authorization",
                    "value": "eyJhbGciOiJIUzI1NiIsInR5cCI6IkpXVCJ9.eyJ1c2VySWQiOiI2Njc5ZDAyOTkzYmNjMjBiNzkzYTM3YzYiLCJyb2xlIjoiYWRtaW4iLCJpYXQiOjE3MTk1MzU3NzcsImV4cCI6MTcxOTUzOTM3N30.q2lfxfRNpAX-r3ErqC04737Fn5AkP0-xqJTAolhnJ9w"
                }
            ],
            "body": {
                "type": "json",
                "raw": "{\n  \"nombre\": \"Pablo\",\n  \"apellido\": \"Gutierrez\",\n  \"dni\": \"12345678\",\n  \"fecha_nacimiento\": \"2000-11-11\",\n  \"curso\": \"Historia\",\n  \"email\": \"fernando.gutierrez@example.com\",\n  \"telefono\": \"1234567890\",\n  \"direccion\": \"Calle de la Luna 123\",\n  \"foto\": \"https://www.w3schools.com/howto/img_avatar.png\",\n  \"regular\": true\n}",
                "form": []
            }
        },
        {
            "_id": "12244ecf-98e7-42d8-8eaf-8721c0afd329",
            "colId": "acd7cf24-efe8-4c6b-887b-795995e3373b",
            "containerId": "b6256980-540b-4557-84a7-a2323ab6a60f",
            "name": "actualizar datos docente por ID",
            "url": "http://localhost:8080/docentes/update-docente/id/66679b097eaa690c24d185a1",
            "method": "PUT",
            "sortNum": 10000,
            "created": "2024-06-11T00:35:52.715Z",
            "modified": "2024-06-28T00:54:49.324Z",
            "headers": [
                {
                    "name": "Authorization",
                    "value": "eyJhbGciOiJIUzI1NiIsInR5cCI6IkpXVCJ9.eyJ1c2VySWQiOiI2Njc5ZDAyOTkzYmNjMjBiNzkzYTM3YzYiLCJyb2xlIjoiYWRtaW4iLCJpYXQiOjE3MTk1MzU3NzcsImV4cCI6MTcxOTUzOTM3N30.q2lfxfRNpAX-r3ErqC04737Fn5AkP0-xqJTAolhnJ9w"
                }
            ],
            "body": {
                "type": "json",
                "raw": "{\n    \"apellido\": \"Schup\"\n}",
                "form": []
            }
        },
        {
            "_id": "4da73422-e9b2-42fe-a4ba-973123269292",
            "colId": "acd7cf24-efe8-4c6b-887b-795995e3373b",
            "containerId": "8237cd96-29ba-4126-be73-e3774cf164c2",
            "name": "cambiar a docente a Con licencia por ID",
            "url": "http://localhost:8080/docentes/licencia/id/66679b017eaa690c24d1859b",
            "method": "DELETE",
            "sortNum": 10000,
            "created": "2024-06-11T01:01:54.807Z",
            "modified": "2024-06-28T00:55:01.415Z",
            "headers": [
                {
                    "name": "Authorization",
                    "value": "eyJhbGciOiJIUzI1NiIsInR5cCI6IkpXVCJ9.eyJ1c2VySWQiOiI2Njc5ZDAyOTkzYmNjMjBiNzkzYTM3YzYiLCJyb2xlIjoiYWRtaW4iLCJpYXQiOjE3MTk1MzU3NzcsImV4cCI6MTcxOTUzOTM3N30.q2lfxfRNpAX-r3ErqC04737Fn5AkP0-xqJTAolhnJ9w"
                }
            ]
        },
        {
            "_id": "9b934f6b-4865-432a-885f-9d8ae474282b",
            "colId": "acd7cf24-efe8-4c6b-887b-795995e3373b",
            "containerId": "beeec0b9-c389-4e5d-891d-29b3afd81c2a",
            "name": "actualizar datos no docente por ID",
            "url": "http://localhost:8080/no-docentes/update-nodocente/id/6672217bdebe03b366ff6509",
            "method": "PUT",
            "sortNum": 10000,
            "created": "2024-06-19T00:07:29.908Z",
            "modified": "2024-06-28T00:56:26.602Z",
            "headers": [
                {
                    "name": "Authorization",
                    "value": "eyJhbGciOiJIUzI1NiIsInR5cCI6IkpXVCJ9.eyJ1c2VySWQiOiI2Njc5ZDAyOTkzYmNjMjBiNzkzYTM3YzYiLCJyb2xlIjoiYWRtaW4iLCJpYXQiOjE3MTk1MzU3NzcsImV4cCI6MTcxOTUzOTM3N30.q2lfxfRNpAX-r3ErqC04737Fn5AkP0-xqJTAolhnJ9w"
                }
            ],
            "body": {
                "type": "json",
                "raw": "{\n    \"licencia\":\"false\"\n}",
                "form": []
            }
        },
        {
            "_id": "6852ef67-b53f-4343-99a0-9669e1b02901",
            "colId": "acd7cf24-efe8-4c6b-887b-795995e3373b",
            "containerId": "38030b89-2218-4627-840c-32124c7d5292",
            "name": "cambiar a no docente a Con licencia por ID",
            "url": "http://localhost:8080/no-docentes/licencia/id/6672217bdebe03b366ff6509",
            "method": "DELETE",
            "sortNum": 10000,
            "created": "2024-06-19T00:07:29.909Z",
            "modified": "2024-06-28T00:56:36.771Z",
            "headers": [
                {
                    "name": "Authorization",
                    "value": "eyJhbGciOiJIUzI1NiIsInR5cCI6IkpXVCJ9.eyJ1c2VySWQiOiI2Njc5ZDAyOTkzYmNjMjBiNzkzYTM3YzYiLCJyb2xlIjoiYWRtaW4iLCJpYXQiOjE3MTk1MzU3NzcsImV4cCI6MTcxOTUzOTM3N30.q2lfxfRNpAX-r3ErqC04737Fn5AkP0-xqJTAolhnJ9w"
                }
            ]
        },
        {
            "_id": "1ee62cb3-2580-4a4e-a86e-0ad8f5456597",
            "colId": "acd7cf24-efe8-4c6b-887b-795995e3373b",
            "containerId": "403a51f5-3e12-40af-944b-e7a1a8bb324f",
            "name": "get artworks",
            "url": "http://localhost:8080/art-api/artworks/",
            "method": "GET",
            "sortNum": 10000,
            "created": "2024-06-19T01:16:04.894Z",
            "modified": "2024-06-25T00:48:34.860Z",
            "headers": [
                {
                    "name": "Authorization",
                    "value": "eyJhbGciOiJIUzI1NiIsInR5cCI6IkpXVCJ9.eyJ1c2VySWQiOiI2Njc0NjRlN2YwZWU4MGVkODgwMjA1ZmEiLCJyb2xlIjoiYWx1bW5vIiwiaWF0IjoxNzE5Mjc2MzgwLCJleHAiOjE3MTkyNzk5ODB9.NtvDVVorKdz5soH45Pd0hOWWuB9wGNffKXTOkV9lwxs"
                }
            ]
        },
        {
            "_id": "bb375cd1-eec8-4e07-b372-5c52effb1a90",
            "colId": "acd7cf24-efe8-4c6b-887b-795995e3373b",
            "containerId": "ac8e27a3-3a81-4e0a-a3a8-0864646e97c3",
            "name": "get artists",
            "url": "http://localhost:8080/art-api/artists",
            "method": "GET",
            "sortNum": 10000,
            "created": "2024-06-19T01:33:43.198Z",
            "modified": "2024-06-25T00:49:21.778Z",
            "headers": [
                {
                    "name": "Authorization",
                    "value": "eyJhbGciOiJIUzI1NiIsInR5cCI6IkpXVCJ9.eyJ1c2VySWQiOiI2Njc0NjRlN2YwZWU4MGVkODgwMjA1ZmEiLCJyb2xlIjoiYWx1bW5vIiwiaWF0IjoxNzE5Mjc2MzgwLCJleHAiOjE3MTkyNzk5ODB9.NtvDVVorKdz5soH45Pd0hOWWuB9wGNffKXTOkV9lwxs"
                }
            ]
        },
        {
            "_id": "0eb47140-1af2-4d85-ada4-c73673b65ab4",
            "colId": "acd7cf24-efe8-4c6b-887b-795995e3373b",
            "containerId": "c5c675f9-2af0-4dc4-a374-3bb4702cdc6f",
            "name": "alumno por id",
            "url": "http://localhost:8080/alumnos/id/6638196aa6845d03f69a62b5",
            "method": "GET",
            "sortNum": 20000,
            "created": "2024-05-05T23:44:47.600Z",
            "modified": "2024-06-28T00:51:02.901Z",
            "headers": [
                {
                    "name": "Authorization",
                    "value": "eyJhbGciOiJIUzI1NiIsInR5cCI6IkpXVCJ9.eyJ1c2VySWQiOiI2Njc5ZDAyOTkzYmNjMjBiNzkzYTM3YzYiLCJyb2xlIjoiYWRtaW4iLCJpYXQiOjE3MTk1MzU3NzcsImV4cCI6MTcxOTUzOTM3N30.q2lfxfRNpAX-r3ErqC04737Fn5AkP0-xqJTAolhnJ9w"
                }
            ]
        },
        {
            "_id": "376adce9-168c-4135-9c5a-c2c2b889c74a",
            "colId": "acd7cf24-efe8-4c6b-887b-795995e3373b",
            "containerId": "8237cd96-29ba-4126-be73-e3774cf164c2",
            "name": "eliminar docente con ID",
            "url": "http://localhost:8080/docentes/delete-docente/id/66679a6aa42a51e589123dd9",
            "method": "DELETE",
            "sortNum": 20000,
            "created": "2024-06-11T01:02:02.696Z",
            "modified": "2024-06-28T00:55:11.082Z",
            "headers": [
                {
                    "name": "Authorization",
                    "value": "eyJhbGciOiJIUzI1NiIsInR5cCI6IkpXVCJ9.eyJ1c2VySWQiOiI2Njc5ZDAyOTkzYmNjMjBiNzkzYTM3YzYiLCJyb2xlIjoiYWRtaW4iLCJpYXQiOjE3MTk1MzU3NzcsImV4cCI6MTcxOTUzOTM3N30.q2lfxfRNpAX-r3ErqC04737Fn5AkP0-xqJTAolhnJ9w"
                }
            ]
        },
        {
            "_id": "830c6856-e3f6-4225-9447-bd6ab78279fb",
            "colId": "acd7cf24-efe8-4c6b-887b-795995e3373b",
            "containerId": "38030b89-2218-4627-840c-32124c7d5292",
            "name": "eliminar no docente con ID",
            "url": "http://localhost:8080/no-docentes/delete-nodocente/id/6672219adebe03b366ff650b",
            "method": "DELETE",
            "sortNum": 20000,
            "created": "2024-06-19T00:07:29.910Z",
            "modified": "2024-06-28T00:56:44.928Z",
            "headers": [
                {
                    "name": "Authorization",
                    "value": "eyJhbGciOiJIUzI1NiIsInR5cCI6IkpXVCJ9.eyJ1c2VySWQiOiI2Njc5ZDAyOTkzYmNjMjBiNzkzYTM3YzYiLCJyb2xlIjoiYWRtaW4iLCJpYXQiOjE3MTk1MzU3NzcsImV4cCI6MTcxOTUzOTM3N30.q2lfxfRNpAX-r3ErqC04737Fn5AkP0-xqJTAolhnJ9w"
                }
            ]
        },
        {
            "_id": "1f768a50-fe44-491c-b7aa-b5ad74a9bd4d",
            "colId": "acd7cf24-efe8-4c6b-887b-795995e3373b",
            "containerId": "403a51f5-3e12-40af-944b-e7a1a8bb324f",
            "name": "get artwork por ID",
            "url": "http://localhost:8080/art-api/artworks/id/125841",
            "method": "GET",
            "sortNum": 20000,
            "created": "2024-06-19T01:23:21.231Z",
            "modified": "2024-06-25T00:48:47.383Z",
            "headers": [
                {
                    "name": "Authorization",
                    "value": "eyJhbGciOiJIUzI1NiIsInR5cCI6IkpXVCJ9.eyJ1c2VySWQiOiI2Njc0NjRlN2YwZWU4MGVkODgwMjA1ZmEiLCJyb2xlIjoiYWx1bW5vIiwiaWF0IjoxNzE5Mjc2MzgwLCJleHAiOjE3MTkyNzk5ODB9.NtvDVVorKdz5soH45Pd0hOWWuB9wGNffKXTOkV9lwxs"
                }
            ]
        },
        {
            "_id": "a35a0474-d449-4ace-9d96-f860e05795f1",
            "colId": "acd7cf24-efe8-4c6b-887b-795995e3373b",
            "containerId": "ac8e27a3-3a81-4e0a-a3a8-0864646e97c3",
            "name": "get artists por ID",
            "url": "http://localhost:8080/art-api/artists/id/36198",
            "method": "GET",
            "sortNum": 20000,
            "created": "2024-06-19T01:33:43.199Z",
            "modified": "2024-06-25T00:49:31.869Z",
            "headers": [
                {
                    "name": "Authorization",
                    "value": "eyJhbGciOiJIUzI1NiIsInR5cCI6IkpXVCJ9.eyJ1c2VySWQiOiI2Njc0NjRlN2YwZWU4MGVkODgwMjA1ZmEiLCJyb2xlIjoiYWx1bW5vIiwiaWF0IjoxNzE5Mjc2MzgwLCJleHAiOjE3MTkyNzk5ODB9.NtvDVVorKdz5soH45Pd0hOWWuB9wGNffKXTOkV9lwxs"
                }
            ]
        },
        {
            "_id": "f05a2752-d635-478f-8c75-431593f82c09",
            "colId": "acd7cf24-efe8-4c6b-887b-795995e3373b",
            "containerId": "c5c675f9-2af0-4dc4-a374-3bb4702cdc6f",
            "name": "alumno por dni",
            "url": "http://localhost:8080/alumnos/dni/01234567",
            "method": "GET",
            "sortNum": 30000,
            "created": "2024-05-05T23:46:01.020Z",
            "modified": "2024-06-28T00:51:26.074Z",
            "headers": [
                {
                    "name": "Authorization",
                    "value": "eyJhbGciOiJIUzI1NiIsInR5cCI6IkpXVCJ9.eyJ1c2VySWQiOiI2Njc5ZDAyOTkzYmNjMjBiNzkzYTM3YzYiLCJyb2xlIjoiYWRtaW4iLCJpYXQiOjE3MTk1MzU3NzcsImV4cCI6MTcxOTUzOTM3N30.q2lfxfRNpAX-r3ErqC04737Fn5AkP0-xqJTAolhnJ9w"
                }
            ]
        },
        {
            "_id": "c4769820-05c4-4765-b69b-3f839eb7e673",
            "colId": "acd7cf24-efe8-4c6b-887b-795995e3373b",
            "containerId": "403a51f5-3e12-40af-944b-e7a1a8bb324f",
            "name": "buscar obra de arte por termino",
            "url": "http://localhost:8080/art-api/artworks/search/cats",
            "method": "GET",
            "sortNum": 30000,
            "created": "2024-06-19T01:25:24.159Z",
            "modified": "2024-06-25T00:49:05.786Z",
            "headers": [
                {
                    "name": "Authorization",
                    "value": "eyJhbGciOiJIUzI1NiIsInR5cCI6IkpXVCJ9.eyJ1c2VySWQiOiI2Njc0NjRlN2YwZWU4MGVkODgwMjA1ZmEiLCJyb2xlIjoiYWx1bW5vIiwiaWF0IjoxNzE5Mjc2MzgwLCJleHAiOjE3MTkyNzk5ODB9.NtvDVVorKdz5soH45Pd0hOWWuB9wGNffKXTOkV9lwxs"
                }
            ]
        },
        {
            "_id": "c80e8db9-9027-4de1-a6ef-80548287292d",
            "colId": "acd7cf24-efe8-4c6b-887b-795995e3373b",
            "containerId": "ac8e27a3-3a81-4e0a-a3a8-0864646e97c3",
            "name": "buscar artistas por termino",
            "url": "http://localhost:8080/art-api/artists/search/picasso",
            "method": "GET",
            "sortNum": 30000,
            "created": "2024-06-19T01:33:43.200Z",
            "modified": "2024-06-25T00:49:45.427Z",
            "headers": [
                {
                    "name": "Authorization",
                    "value": "eyJhbGciOiJIUzI1NiIsInR5cCI6IkpXVCJ9.eyJ1c2VySWQiOiI2Njc0NjRlN2YwZWU4MGVkODgwMjA1ZmEiLCJyb2xlIjoiYWx1bW5vIiwiaWF0IjoxNzE5Mjc2MzgwLCJleHAiOjE3MTkyNzk5ODB9.NtvDVVorKdz5soH45Pd0hOWWuB9wGNffKXTOkV9lwxs"
                }
            ]
        },
        {
            "_id": "16f8a92f-1340-4dd7-be06-80ce8f0435ea",
            "colId": "acd7cf24-efe8-4c6b-887b-795995e3373b",
            "containerId": "b0b7201e-c5c9-4a14-909b-6bb1285674b2",
            "name": "actualizar datos alumno por id",
            "url": "http://localhost:8080/alumnos/update-alumno/id/6638189cc1d8c32ae013eb6a",
            "method": "PUT",
            "sortNum": 40000,
            "created": "2024-05-05T23:48:16.197Z",
            "modified": "2024-06-28T00:52:12.545Z",
            "headers": [
                {
                    "name": "Authorization",
                    "value": "eyJhbGciOiJIUzI1NiIsInR5cCI6IkpXVCJ9.eyJ1c2VySWQiOiI2Njc5ZDAyOTkzYmNjMjBiNzkzYTM3YzYiLCJyb2xlIjoiYWRtaW4iLCJpYXQiOjE3MTk1MzU3NzcsImV4cCI6MTcxOTUzOTM3N30.q2lfxfRNpAX-r3ErqC04737Fn5AkP0-xqJTAolhnJ9w"
                }
            ],
            "body": {
                "type": "json",
                "raw": "{\n  \"curso\": \"Literatura\"\n}",
                "form": []
            }
        },
        {
            "_id": "f744fe3e-53f9-40db-bcd7-df59fec702c9",
            "colId": "acd7cf24-efe8-4c6b-887b-795995e3373b",
            "containerId": "005ff324-7ba4-421d-91b8-90121202e59f",
            "name": "cambiar a alumno irregular por id",
            "url": "http://localhost:8080/alumnos/irregular/id/6638189cc1d8c32ae013eb6a",
            "method": "DELETE",
            "sortNum": 50000,
            "created": "2024-05-05T23:52:40.785Z",
            "modified": "2024-06-28T00:52:40.862Z",
            "headers": [
                {
                    "name": "Authorization",
                    "value": "eyJhbGciOiJIUzI1NiIsInR5cCI6IkpXVCJ9.eyJ1c2VySWQiOiI2Njc5ZDAyOTkzYmNjMjBiNzkzYTM3YzYiLCJyb2xlIjoiYWRtaW4iLCJpYXQiOjE3MTk1MzU3NzcsImV4cCI6MTcxOTUzOTM3N30.q2lfxfRNpAX-r3ErqC04737Fn5AkP0-xqJTAolhnJ9w"
                }
            ]
        },
        {
            "_id": "0a7939d1-9497-490c-a63d-4b24e16c4a9c",
            "colId": "acd7cf24-efe8-4c6b-887b-795995e3373b",
            "containerId": "005ff324-7ba4-421d-91b8-90121202e59f",
            "name": "eliminar alumno por id",
            "url": "http://localhost:8080/alumnos/delete-alumno/id/66381c564672cbf375a0b2d4",
            "method": "DELETE",
            "sortNum": 60000,
            "created": "2024-05-05T23:55:14.062Z",
            "modified": "2024-06-28T00:52:56.099Z",
            "headers": [
                {
                    "name": "Authorization",
                    "value": "eyJhbGciOiJIUzI1NiIsInR5cCI6IkpXVCJ9.eyJ1c2VySWQiOiI2Njc5ZDAyOTkzYmNjMjBiNzkzYTM3YzYiLCJyb2xlIjoiYWRtaW4iLCJpYXQiOjE3MTk1MzU3NzcsImV4cCI6MTcxOTUzOTM3N30.q2lfxfRNpAX-r3ErqC04737Fn5AkP0-xqJTAolhnJ9w"
                }
            ]
        },
        {
            "_id": "85c883d8-4f29-4f5a-95eb-6e2de14ed3a0",
            "colId": "acd7cf24-efe8-4c6b-887b-795995e3373b",
            "containerId": "d6da219b-947c-4ff8-9cad-4241c077db91",
            "name": "crear alumno random",
            "url": "http://localhost:8080/alumnos/new-alumno-random",
            "method": "POST",
            "sortNum": 70000,
            "created": "2024-05-06T00:09:45.676Z",
            "modified": "2024-05-06T00:10:19.601Z",
            "headers": []
        },
        {
            "_id": "fd466a53-33a3-4b61-8b9f-43a53e4c7b3a",
            "colId": "acd7cf24-efe8-4c6b-887b-795995e3373b",
            "containerId": "0cdee016-4572-4e9e-8a24-ace4fd3f6256",
            "name": "lista de docentes",
            "url": "http://localhost:8080/docentes",
            "method": "GET",
            "sortNum": 80000,
            "created": "2024-06-11T00:22:46.529Z",
            "modified": "2024-06-28T00:53:51.009Z",
            "headers": [
                {
                    "name": "Authorization",
                    "value": "eyJhbGciOiJIUzI1NiIsInR5cCI6IkpXVCJ9.eyJ1c2VySWQiOiI2Njc5ZDAyOTkzYmNjMjBiNzkzYTM3YzYiLCJyb2xlIjoiYWRtaW4iLCJpYXQiOjE3MTk1MzU3NzcsImV4cCI6MTcxOTUzOTM3N30.q2lfxfRNpAX-r3ErqC04737Fn5AkP0-xqJTAolhnJ9w"
                }
            ]
        },
        {
            "_id": "915bbca2-cd55-4ebe-95b7-d59408009217",
            "colId": "acd7cf24-efe8-4c6b-887b-795995e3373b",
            "containerId": "0e1e6492-9623-4a2b-9873-1c4f05bd5d60",
            "name": "lista de no docentes",
            "url": "http://localhost:8080/no-docentes",
            "method": "GET",
            "sortNum": 80000,
            "created": "2024-06-19T00:07:29.905Z",
            "modified": "2024-06-28T00:55:54.712Z",
            "headers": [
                {
                    "name": "Authorization",
                    "value": "eyJhbGciOiJIUzI1NiIsInR5cCI6IkpXVCJ9.eyJ1c2VySWQiOiI2Njc5ZDAyOTkzYmNjMjBiNzkzYTM3YzYiLCJyb2xlIjoiYWRtaW4iLCJpYXQiOjE3MTk1MzU3NzcsImV4cCI6MTcxOTUzOTM3N30.q2lfxfRNpAX-r3ErqC04737Fn5AkP0-xqJTAolhnJ9w"
                }
            ]
        },
        {
            "_id": "15211955-b85c-4517-9220-dc44e32d805a",
            "colId": "acd7cf24-efe8-4c6b-887b-795995e3373b",
            "containerId": "0cdee016-4572-4e9e-8a24-ace4fd3f6256",
            "name": "docente por ID",
            "url": "http://localhost:8080/docentes/id/66679b097eaa690c24d185a1",
            "method": "GET",
            "sortNum": 90000,
            "created": "2024-06-11T00:33:34.096Z",
            "modified": "2024-06-28T00:54:19.544Z",
            "headers": [
                {
                    "name": "Authorization",
                    "value": "eyJhbGciOiJIUzI1NiIsInR5cCI6IkpXVCJ9.eyJ1c2VySWQiOiI2Njc5ZDAyOTkzYmNjMjBiNzkzYTM3YzYiLCJyb2xlIjoiYWRtaW4iLCJpYXQiOjE3MTk1MzU3NzcsImV4cCI6MTcxOTUzOTM3N30.q2lfxfRNpAX-r3ErqC04737Fn5AkP0-xqJTAolhnJ9w"
                }
            ]
        },
        {
            "_id": "8998915b-3320-4fb1-86cc-44c381d34fa1",
            "colId": "acd7cf24-efe8-4c6b-887b-795995e3373b",
            "containerId": "0e1e6492-9623-4a2b-9873-1c4f05bd5d60",
            "name": "no docente por ID",
            "url": "http://localhost:8080/no-docentes/id/6672217bdebe03b366ff6509",
            "method": "GET",
            "sortNum": 90000,
            "created": "2024-06-19T00:07:29.906Z",
            "modified": "2024-06-28T00:56:06.852Z",
            "headers": [
                {
                    "name": "Authorization",
                    "value": "eyJhbGciOiJIUzI1NiIsInR5cCI6IkpXVCJ9.eyJ1c2VySWQiOiI2Njc5ZDAyOTkzYmNjMjBiNzkzYTM3YzYiLCJyb2xlIjoiYWRtaW4iLCJpYXQiOjE3MTk1MzU3NzcsImV4cCI6MTcxOTUzOTM3N30.q2lfxfRNpAX-r3ErqC04737Fn5AkP0-xqJTAolhnJ9w"
                }
            ]
        },
        {
            "_id": "4d5e02f0-2910-43ac-bd77-f65b42c7f26b",
            "colId": "acd7cf24-efe8-4c6b-887b-795995e3373b",
            "containerId": "40dd61a0-d1f9-45ff-bd7a-9146dd3c52c8",
            "name": "crear docente nuevo",
            "url": "http://localhost:8080/docentes/new-docente",
            "method": "POST",
            "sortNum": 100000,
            "created": "2024-06-11T00:23:55.272Z",
            "modified": "2024-06-28T00:53:20.116Z",
            "headers": [
                {
                    "name": "Authorization",
                    "value": "eyJhbGciOiJIUzI1NiIsInR5cCI6IkpXVCJ9.eyJ1c2VySWQiOiI2Njc5ZDAyOTkzYmNjMjBiNzkzYTM3YzYiLCJyb2xlIjoiYWRtaW4iLCJpYXQiOjE3MTk1MzU3NzcsImV4cCI6MTcxOTUzOTM3N30.q2lfxfRNpAX-r3ErqC04737Fn5AkP0-xqJTAolhnJ9w"
                }
            ],
            "body": {
                "type": "json",
                "raw": "{\n  \"nombre\": \"Fernando\",\n  \"apellido\": \"Gutierrez\",\n  \"dni\": \"12345678\",\n  \"fecha_nacimiento\": \"2000-11-11\",\n  \"curso\": \"Arte\",\n  \"email\": \"fernando.gutierrez@example.com\",\n  \"telefono\": \"1234567890\",\n  \"direccion\": \"Calle de la Luna 123\",\n  \"foto\": \"https://www.w3schools.com/howto/img_avatar.png\"\n}",
                "form": []
            }
        },
        {
            "_id": "d3b7908c-118d-4e04-b08c-c81beaf71942",
            "colId": "acd7cf24-efe8-4c6b-887b-795995e3373b",
            "containerId": "0cdee016-4572-4e9e-8a24-ace4fd3f6256",
            "name": "docente por DNI",
            "url": "http://localhost:8080/docentes/dni/48367461",
            "method": "GET",
            "sortNum": 100000,
            "created": "2024-06-11T00:33:43.040Z",
            "modified": "2024-06-28T00:54:30.232Z",
            "headers": [
                {
                    "name": "Authorization",
                    "value": "eyJhbGciOiJIUzI1NiIsInR5cCI6IkpXVCJ9.eyJ1c2VySWQiOiI2Njc5ZDAyOTkzYmNjMjBiNzkzYTM3YzYiLCJyb2xlIjoiYWRtaW4iLCJpYXQiOjE3MTk1MzU3NzcsImV4cCI6MTcxOTUzOTM3N30.q2lfxfRNpAX-r3ErqC04737Fn5AkP0-xqJTAolhnJ9w"
                }
            ]
        },
        {
            "_id": "54a054b4-a407-42e5-8431-a36e17f3b7f2",
            "colId": "acd7cf24-efe8-4c6b-887b-795995e3373b",
            "containerId": "8d1a19db-8fe5-4741-a48f-95730d640308",
            "name": "crear no docente nuevo",
            "url": "http://localhost:8080/no-docentes/new-nodocente",
            "method": "POST",
            "sortNum": 100000,
            "created": "2024-06-19T00:07:29.903Z",
            "modified": "2024-06-28T00:55:24.310Z",
            "headers": [
                {
                    "name": "Authorization",
                    "value": "eyJhbGciOiJIUzI1NiIsInR5cCI6IkpXVCJ9.eyJ1c2VySWQiOiI2Njc5ZDAyOTkzYmNjMjBiNzkzYTM3YzYiLCJyb2xlIjoiYWRtaW4iLCJpYXQiOjE3MTk1MzU3NzcsImV4cCI6MTcxOTUzOTM3N30.q2lfxfRNpAX-r3ErqC04737Fn5AkP0-xqJTAolhnJ9w"
                }
            ],
            "body": {
                "type": "json",
                "raw": "{\n  \"nombre\": \"Fernando\",\n  \"apellido\": \"Gutierrez\",\n  \"dni\": \"12345678\",\n  \"fecha_nacimiento\": \"2000-11-11\",\n  \"email\": \"fernando.gutierrez@example.com\",\n  \"telefono\": \"1234567890\",\n  \"direccion\": \"Calle de la Luna 123\",\n  \"foto\": \"https://www.w3schools.com/howto/img_avatar.png\"\n}",
                "form": []
            }
        },
        {
            "_id": "d4dbdd22-01dc-42fc-a2ef-800f065baae1",
            "colId": "acd7cf24-efe8-4c6b-887b-795995e3373b",
            "containerId": "0e1e6492-9623-4a2b-9873-1c4f05bd5d60",
            "name": "no docente por DNI",
            "url": "http://localhost:8080/no-docentes/dni/12345678",
            "method": "GET",
            "sortNum": 100000,
            "created": "2024-06-19T00:07:29.907Z",
            "modified": "2024-06-28T00:56:17.014Z",
            "headers": [
                {
                    "name": "Authorization",
                    "value": "eyJhbGciOiJIUzI1NiIsInR5cCI6IkpXVCJ9.eyJ1c2VySWQiOiI2Njc5ZDAyOTkzYmNjMjBiNzkzYTM3YzYiLCJyb2xlIjoiYWRtaW4iLCJpYXQiOjE3MTk1MzU3NzcsImV4cCI6MTcxOTUzOTM3N30.q2lfxfRNpAX-r3ErqC04737Fn5AkP0-xqJTAolhnJ9w"
                }
            ]
        },
        {
            "_id": "2978cc9d-50a1-43aa-a15d-b7b54895b593",
            "colId": "acd7cf24-efe8-4c6b-887b-795995e3373b",
            "containerId": "40dd61a0-d1f9-45ff-bd7a-9146dd3c52c8",
            "name": "crear docente random",
            "url": "http://localhost:8080/docentes/new-docente-random",
            "method": "POST",
            "sortNum": 110000,
            "created": "2024-06-11T00:26:57.650Z",
            "modified": "2024-06-11T00:27:37.847Z",
            "headers": []
        },
        {
            "_id": "c941e424-b4f6-450f-8e3f-5f0ac21a55e0",
            "colId": "acd7cf24-efe8-4c6b-887b-795995e3373b",
            "containerId": "8d1a19db-8fe5-4741-a48f-95730d640308",
            "name": "crear no docente random",
            "url": "http://localhost:8080/no-docentes/new-nodocente-random",
            "method": "POST",
            "sortNum": 110000,
            "created": "2024-06-19T00:07:29.904Z",
            "modified": "2024-06-28T00:55:39.815Z",
            "headers": []
        },
        {
            "_id": "b658668c-18b6-49a8-81a6-c5e2fd101fb8",
            "colId": "acd7cf24-efe8-4c6b-887b-795995e3373b",
            "containerId": "d608f91a-2d32-482a-a07e-d829c7530543",
            "name": "lista de paises",
            "url": "http://localhost:8080/countries-api/countries",
            "method": "GET",
            "sortNum": 150000,
            "created": "2024-06-19T01:55:46.355Z",
            "modified": "2024-06-25T00:47:27.359Z",
            "headers": [
                {
                    "name": "Authorization",
                    "value": "eyJhbGciOiJIUzI1NiIsInR5cCI6IkpXVCJ9.eyJ1c2VySWQiOiI2Njc0NjRlN2YwZWU4MGVkODgwMjA1ZmEiLCJyb2xlIjoiYWx1bW5vIiwiaWF0IjoxNzE5Mjc2MzgwLCJleHAiOjE3MTkyNzk5ODB9.NtvDVVorKdz5soH45Pd0hOWWuB9wGNffKXTOkV9lwxs"
                }
            ]
        },
        {
            "_id": "ffa238c2-b938-4eea-b890-cf288f56f1dd",
            "colId": "acd7cf24-efe8-4c6b-887b-795995e3373b",
            "containerId": "d608f91a-2d32-482a-a07e-d829c7530543",
            "name": "info de paises segun su codigo",
            "url": "http://localhost:8080/countries-api/countries/code/AR",
            "method": "GET",
            "sortNum": 160000,
            "created": "2024-06-19T01:56:02.629Z",
            "modified": "2024-06-25T00:47:55.362Z",
            "headers": [
                {
                    "name": "Authorization",
                    "value": "eyJhbGciOiJIUzI1NiIsInR5cCI6IkpXVCJ9.eyJ1c2VySWQiOiI2Njc0NjRlN2YwZWU4MGVkODgwMjA1ZmEiLCJyb2xlIjoiYWx1bW5vIiwiaWF0IjoxNzE5Mjc2MzgwLCJleHAiOjE3MTkyNzk5ODB9.NtvDVVorKdz5soH45Pd0hOWWuB9wGNffKXTOkV9lwxs"
                }
            ]
        },
        {
            "_id": "4614113e-d1bc-495b-aab5-1ce1210d7584",
            "colId": "acd7cf24-efe8-4c6b-887b-795995e3373b",
            "containerId": "d608f91a-2d32-482a-a07e-d829c7530543",
            "name": "feriados de paises segun año y codigo",
            "url": "http://localhost:8080/countries-api/holidays/AR/2024",
            "method": "GET",
            "sortNum": 170000,
            "created": "2024-06-19T01:56:21.491Z",
            "modified": "2024-06-25T00:48:05.697Z",
            "headers": [
                {
                    "name": "Authorization",
                    "value": "eyJhbGciOiJIUzI1NiIsInR5cCI6IkpXVCJ9.eyJ1c2VySWQiOiI2Njc0NjRlN2YwZWU4MGVkODgwMjA1ZmEiLCJyb2xlIjoiYWx1bW5vIiwiaWF0IjoxNzE5Mjc2MzgwLCJleHAiOjE3MTkyNzk5ODB9.NtvDVVorKdz5soH45Pd0hOWWuB9wGNffKXTOkV9lwxs"
                }
            ]
        },
        {
            "_id": "c6d3b977-f584-435a-962a-230e0358619d",
            "colId": "acd7cf24-efe8-4c6b-887b-795995e3373b",
            "containerId": "46483a8d-9564-4ce1-ba2e-005391676123",
            "name": "login",
            "url": "http://localhost:8080/auth/login",
            "method": "POST",
            "sortNum": 180000,
            "created": "2024-06-20T17:17:23.392Z",
            "modified": "2024-06-28T00:49:37.448Z",
            "headers": [],
            "body": {
                "type": "json",
                "raw": "{\n  \"email\": \"pepito4@gmail.com\",\n  \"password\": \"1234\"\n}",
                "form": []
            }
        },
        {
            "_id": "1c52feaa-775a-4147-9c96-c876ff63dfcb",
            "colId": "acd7cf24-efe8-4c6b-887b-795995e3373b",
            "containerId": "46483a8d-9564-4ce1-ba2e-005391676123",
            "name": "register",
            "url": "http://localhost:8080/auth/register",
            "method": "POST",
            "sortNum": 190000,
            "created": "2024-06-20T17:18:37.290Z",
            "modified": "2024-06-24T19:59:38.013Z",
            "headers": [],
            "body": {
                "type": "json",
                "raw": "{\n  \"email\": \"pepito4@gmail.com\",\n  \"password\": \"1234\",\n  \"role\":\"admin\"\n}",
                "form": []
            }
        },
        {
            "_id": "bdd93afa-f483-4cc8-abfd-060be267beac",
            "colId": "acd7cf24-efe8-4c6b-887b-795995e3373b",
            "containerId": "46483a8d-9564-4ce1-ba2e-005391676123",
            "name": "users list",
            "url": "http://localhost:8080/auth/users",
            "method": "GET",
            "sortNum": 200000,
            "created": "2024-06-20T18:03:29.340Z",
            "modified": "2024-06-20T18:03:38.935Z",
            "headers": []
        },
        {
            "_id": "8d8689db-c37b-4c4e-9baf-21f17703e0d6",
            "colId": "acd7cf24-efe8-4c6b-887b-795995e3373b",
            "containerId": "46483a8d-9564-4ce1-ba2e-005391676123",
            "name": "logout",
            "url": "http://localhost:8080/auth/logout",
            "method": "POST",
            "sortNum": 210000,
            "created": "2024-06-20T21:28:36.994Z",
            "modified": "2024-06-20T21:28:54.185Z",
            "headers": []
        }
    ],
    "ref": "uV8Sj708XhI8zpsTMYdCh7OVyAA7rIIcfmzER5FJhj9lOv1iuKL8NQvpqGTxpExgid1RdHO6qmlG2vCBWFhnMg"
}